setup.cfg
setup.py
ArcUUID/ArcUUID.py
ArcUUID/Ids.py
ArcUUID/__init__.py
py_arc_identifiers.egg-info/PKG-INFO
py_arc_identifiers.egg-info/SOURCES.txt
py_arc_identifiers.egg-info/dependency_links.txt
py_arc_identifiers.egg-info/top_level.txt
test/ArcUUIDTest.py
test/TestOne.py
test/__init__.py