Metadata-Version: 1.1
Name: py-arc-identifiers
Version: 0.3
Summary: generate Arc UUIDs in python
Home-page: https://github.com/WPMedia/py-arc-identifiers
Author: patharer
Author-email: rohan.pathare@washpost.com
License: MIT
Download-URL: https://github.com/WPMedia/py-arc-identifiers/tarball/0.3
Platform: UNKNOWN
